{
  "ipo_status": "Closed",
  "ticker_code": "CMNT",
  "image": "",
  "company_name": "PT Cemindo Gemilang Tbk",
  "sector": "Basic Materials",
  "subsector": "Construction Materials",
  "listing_board": "Utama",
  "final_price": 680.0,
  "line_of_business": "Industri Semen",
  "address": "Jl, Raya Pluit Selatan Blok S No, 8 I-J RT022/RW008, Penjaringan Jakarta Utara 14440, Indonesia",
  "website": "https://www.semenmerahputih.com",
  "number_of_shares_offered": 1718800000,
  "%_of_total_shares": 10.04,
  "participant_admin": {
    "code": "KI",
    "name": "CIPTADANA SEKURITAS ASIA"
  },
  "book_building_opening": "09/08/2021",
  "book_building_closing": "19/08/2021",
  "lowest_book_building_price": 600,
  "highest_book_building_price": 800,
  "opening_of_offering_period": "02/09/2021",
  "closing_of_offering_period": "06/09/2021",
  "closing_date": "06/09/2021",
  "distribution_date": "07/09/2021",
  "listing_date": "08/09/2021",
  "ara_arb_percentage": "25%",
  "underwriters": [
    {
      "code": "KI",
      "name": "CIPTADANA SEKURITAS ASIA",
      "percentage": ""
    },
    {
      "code": "CC",
      "name": "MANDIRI SEKURITAS",
      "percentage": ""
    }
  ],
  "warrant": {
    "code": "",
    "per_share_ratio": 0.0,
    "exercise_price_(rp)": "",
    "open": "",
    "high": "",
    "low": "",
    "close": ""
  },
  "listing_price": {
    "open": 700.0,
    "high": 850.0,
    "low": 700.0,
    "close": 850.0,
    "change": 170.0,
    "percentage_change": "25.00%",
    "volume": 84199200.0
  },
  "performa": {
    "1D": "25%",
    "1W": "20%",
    "1M": "39%",
    "6M": "55%",
    "1Y": "49%",
    "updated_at": "31 Juli 2024",
    "source": "https://www.idx.co.id/id/perusahaan-tercatat/kinerja-saham-tercatat-baru/"
  },
  "fundamental": {
    "aset_percentage": "-3%",
    "liabilitas_percentage": "-2%",
    "pendapatan_percentage": "17%",
    "laba_bersih_percentage": "-135%",
    "updated_at": "31 Juli 2024",
    "source": "https://www.idx.co.id/id/perusahaan-tercatat/kinerja-saham-tercatat-baru/"
  }
}
