{
    "ipo_status": "Closed",
    "ticker_code": "UVCR",
    "image": "",
    "company_name": "PT Trimegah Karya Pratama Tbk",
    "sector": "Technology",
    "subsector": "Online Applications & Services",
    "listing_board": "Pengembangan",
    "final_price": 100.0,
    "line_of_business": "Perdagangan Voucher Digital dan Jasa Teknologi",
    "address": "Jl, Tebet Barat IX Nomor 35 BB, Tebet Barat, Jakarta Selatan, 12810",
    "website": "https://ultravoucher.co.id/",
    "number_of_shares_offered": 500000000,
    "%_of_total_shares": 25.0,
    "participant_admin": {
        "code": "SF",
        "name": "SURYA FAJAR SEKURITAS"
    },
    "book_building_opening": "29/06/2021",
    "book_building_closing": "06/07/2021",
    "lowest_book_building_price": 100,
    "highest_book_building_price": 130,
    "opening_of_offering_period": "19/07/2021",
    "closing_of_offering_period": "23/07/2021",
    "closing_date": "23/07/2021",
    "distribution_date": "26/07/2021",
    "listing_date": "27/07/2021",
    "ara_arb_percentage": "35%",
    "underwriters": [
        {
            "code": "SF",
            "name": "SURYA FAJAR SEKURITAS",
            "percentage": ""
        },
        {
            "code": "XA",
            "name": "NH KORINDO SEKURITAS INDONESIA",
            "percentage": ""
        },
        {
            "code": "YP",
            "name": "MIRAE ASSET SEKURITAS INDONESIA",
            "percentage": ""
        }
    ],
    "warrant": {
        "code": "UVCR-W",
        "per_share_ratio": 0.5,
        "exercise_price_(rp)": 350.0,
        "open": "-",
        "high": "-",
        "low": "-",
        "close": "-"
    },
    "listing_price": {
        "open": 110.0,
        "high": 110.0,
        "low": 110.0,
        "close": 110.0,
        "change": 10.0,
        "percentage_change": "10.00%",
        "volume": 6751500.0
    },
    "performa": {
        "1D": "10%",
        "1W": "60%",
        "1M": "374%",
        "6M": "228%",
        "1Y": "43%",
        "updated_at": "31 Juli 2024",
        "source": "https://www.idx.co.id/id/perusahaan-tercatat/kinerja-saham-tercatat-baru/"
    },
    "fundamental": {
        "aset_percentage": "13%",
        "liabilitas_percentage": "9%",
        "pendapatan_percentage": "30%",
        "laba_bersih_percentage": "113%",
        "updated_at": "31 Juli 2024",
        "source": "https://www.idx.co.id/id/perusahaan-tercatat/kinerja-saham-tercatat-baru/"
    }
}